{
 "SoundBanksInfo": {
  "Platform": "Mac",
  "BasePlatform": "Mac",
  "SchemaVersion": "16",
  "SoundBankVersion": "145",
  "SoundBanks": [
   {
    "Id": "3814800052",
    "Type": "Bus",
    "GUID": "{37B304F5-72C5-4988-84FA-0475BEFB7C26}",
    "Language": "SFX",
    "Hash": "{277F9DDD-9BFE-7C35-DB21-2004F1009564}",
    "ObjectPath": "Highrise_Room",
    "ShortName": "Highrise_Room",
    "Path": "Bus/Highrise_Room.bnk",
    "Plugins": {
     "ShareSets": [
      {
       "Id": "1990128658",
       "Name": "Room_Medium",
       "ObjectPath": "\\Effects\\Factory Effects\\RoomVerb\\Rooms\\Room_Medium",
       "GUID": "{F5C06EC1-E4A4-4332-A7D3-A89E2986B74F}",
       "LibName": "Wwise RoomVerb",
       "LibId": "7733251"
      }
     ]
    },
    "AuxBusses": [
     {
      "Id": "3814800052",
      "Name": "Highrise_Room",
      "ObjectPath": "\\Master-Mixer Hierarchy\\Default Work Unit\\Master Audio Bus\\Diegetic\\Auxiliaries\\Highrise\\Highrise_Room",
      "GUID": "{37B304F5-72C5-4988-84FA-0475BEFB7C26}",
      "PluginRefs": {
       "ShareSets": [
        {
         "Id": "1990128658"
        }
       ]
      }
     }
    ]
   }
  ],
  "FileHash": "{6F761C6E-7E30-7ECB-8C08-D4048FC0399B}"
 }
}