{
 "SoundBanksInfo": {
  "Platform": "Mac",
  "BasePlatform": "Mac",
  "SchemaVersion": "16",
  "SoundBankVersion": "145",
  "SoundBanks": [
   {
    "Id": "896607520",
    "Type": "Event",
    "GUID": "{4EB32937-10C0-4BF9-8927-C5BC30E52ED9}",
    "Language": "SFX",
    "Hash": "{C20D0EE0-5104-3705-5017-A15FD3D8F7F1}",
    "ObjectPath": "AMB_UnrealHolograph_FadeIn_OS",
    "ShortName": "AMB_UnrealHolograph_FadeIn_OS",
    "Path": "Event/AMB_UnrealHolograph_FadeIn_OS.bnk",
    "Media": [
     {
      "Id": "619272686",
      "Language": "SFX",
      "Streaming": "false",
      "Location": "Loose",
      "ShortName": "Emitters_UnrealHolograph_FadeIn_OS.wav",
      "Path": "Media/619272686.wem",
      "CachePath": "SFX/Emitters_UnrealHolograph_FadeIn_OS_5920140F.wem"
     }
    ],
    "Events": [
     {
      "Id": "896607520",
      "Name": "AMB_UnrealHolograph_FadeIn_OS",
      "ObjectPath": "\\Events\\Ambience\\Emitters\\Highrise\\Static\\AMB_UnrealHolograph_FadeIn_OS",
      "GUID": "{4EB32937-10C0-4BF9-8927-C5BC30E52ED9}",
      "MaxAttenuation": "8700",
      "DurationType": "OneShot",
      "DurationMin": "6.233227",
      "DurationMax": "6.233227",
      "MediaRefs": [
       {
        "Id": "619272686"
       }
      ]
     }
    ]
   }
  ],
  "FileHash": "{14A04BE2-9FCF-9BD1-815C-33135762E0C3}"
 }
}