{
 "SoundBanksInfo": {
  "Platform": "Mac",
  "BasePlatform": "Mac",
  "SchemaVersion": "16",
  "SoundBankVersion": "145",
  "SoundBanks": [
   {
    "Id": "849782850",
    "Type": "Event",
    "GUID": "{D351862C-9224-46EA-B214-195532B40959}",
    "Language": "SFX",
    "Hash": "{34DDB357-D100-826C-7A05-8E4BFB233DD3}",
    "ObjectPath": "FOL_FallWhoosh",
    "ShortName": "FOL_FallWhoosh",
    "Path": "Event/FOL_FallWhoosh.bnk",
    "Media": [
     {
      "Id": "616719576",
      "Language": "SFX",
      "Streaming": "false",
      "Location": "Loose",
      "ShortName": "FOL_FallWhoosh_LP.wav",
      "Path": "Media/616719576.wem",
      "CachePath": "SFX/FOL_FallWhoosh_LP_E91F277A.wem"
     }
    ],
    "Events": [
     {
      "Id": "849782850",
      "Name": "FOL_FallWhoosh",
      "ObjectPath": "\\Events\\Foley\\Players\\FOL_FallWhoosh",
      "GUID": "{D351862C-9224-46EA-B214-195532B40959}",
      "DurationType": "Infinite",
      "MediaRefs": [
       {
        "Id": "616719576"
       }
      ]
     }
    ]
   }
  ],
  "FileHash": "{7308698F-137E-F522-F34A-E283C11724F7}"
 }
}