<?xml version="1.0" encoding="utf-8"?>
<SoundBanksInfo Platform="Windows" BasePlatform="Windows" SchemaVersion="16" SoundBankVersion="145">
	<SoundBanks>
		<SoundBank Id="2992962930" Type="Event" GUID="{3C0DA367-FE08-40AC-B96C-0BCFE38BE080}" Language="SFX" Hash="{D07382C2-0248-260C-676E-6871E0B864B4}">
			<ObjectPath>AMB_BarrierFence</ObjectPath>
			<ShortName>AMB_BarrierFence</ShortName>
			<Path>Event/AMB_BarrierFence.bnk</Path>
			<Media>
				<File Id="1041432378" Language="SFX" Streaming="false" Location="Loose">
					<ShortName>AMB_BarrierFence_LP.wav</ShortName>
					<Path>Media/1041432378.wem</Path>
					<CachePath>SFX/AMB_BarrierFence_LP_3860FEB7.wem</CachePath>
				</File>
			</Media>
			<Events>
				<Event Id="2992962930" Name="AMB_BarrierFence" ObjectPath="\Events\Ambience\Emitters\Highrise\BarrierFence\AMB_BarrierFence" GUID="{3C0DA367-FE08-40AC-B96C-0BCFE38BE080}" MaxAttenuation="2000" DurationType="Infinite">
					<MediaRefs>
						<MediaRef Id="1041432378"/>
					</MediaRefs>
				</Event>
			</Events>
		</SoundBank>
	</SoundBanks>
	<FileHash>{EE1EE705-F695-59F2-47C7-26D5AAE120F8}</FileHash>
</SoundBanksInfo>
