{
 "SoundBanksInfo": {
  "Platform": "Windows",
  "BasePlatform": "Windows",
  "SchemaVersion": "16",
  "SoundBankVersion": "145",
  "SoundBanks": [
   {
    "Id": "85412153",
    "Type": "User",
    "GUID": "{BCB53ACE-11FB-4F41-BC46-CEE7FE13EED1}",
    "Language": "SFX",
    "Hash": "{85C8678B-D164-C5AC-B90A-448EF2968EFA}",
    "ObjectPath": "\\SoundBanks\\Ambience\\Ambience",
    "ShortName": "Ambience",
    "Path": "Ambience.bnk"
   }
  ],
  "FileHash": "{A29A60FC-C252-445E-F1B9-F75258F112CA}"
 }
}