{
 "SoundBanksInfo": {
  "Platform": "Windows",
  "BasePlatform": "Windows",
  "SchemaVersion": "16",
  "SoundBankVersion": "145",
  "SoundBanks": [
   {
    "Id": "1467963052",
    "Type": "User",
    "GUID": "{DC93E019-DD16-4986-955C-DC3CA3F54DB8}",
    "Language": "SFX",
    "Hash": "{31AA3802-E00F-04E0-F77F-A27F15F5841B}",
    "ObjectPath": "\\SoundBanks\\Weapons\\Weapons",
    "ShortName": "Weapons",
    "Path": "Weapons.bnk",
    "Media": [
     {
      "Id": "14501665",
      "Language": "SFX",
      "Streaming": "false",
      "Location": "Memory",
      "ShortName": "AR_Shot_Tail_Room.wav",
      "CachePath": "SFX/AR_Shot_Tail_Room_10C4C929.wem"
     },
     {
      "Id": "166846503",
      "Language": "SFX",
      "Streaming": "false",
      "Location": "Memory",
      "ShortName": "AR_Shot_Pulse.wav",
      "CachePath": "SFX/AR_Shot_Pulse_10C4C929.wem"
     },
     {
      "Id": "175929226",
      "Language": "SFX",
      "Streaming": "false",
      "Location": "Memory",
      "ShortName": "AR_Shot_Tail_Atrium.wav",
      "CachePath": "SFX/AR_Shot_Tail_Atrium_10C4C929.wem"
     },
     {
      "Id": "228004887",
      "Language": "SFX",
      "Streaming": "false",
      "Location": "Memory",
      "ShortName": "AR_Shot_Transient.wav",
      "CachePath": "SFX/AR_Shot_Transient_10C4C929.wem"
     },
     {
      "Id": "304041726",
      "Language": "SFX",
      "Streaming": "false",
      "Location": "Memory",
      "ShortName": "AR_Dryfire.wav",
      "CachePath": "SFX/AR_Dryfire_10C4C929.wem"
     },
     {
      "Id": "345176474",
      "Language": "SFX",
      "Streaming": "false",
      "Location": "Memory",
      "ShortName": "AR_Shot_LFE.wav",
      "CachePath": "SFX/AR_Shot_LFE_10C4C929.wem"
     },
     {
      "Id": "373309000",
      "Language": "SFX",
      "Streaming": "false",
      "Location": "Memory",
      "ShortName": "AR_Shot_Mech.wav",
      "CachePath": "SFX/AR_Shot_Mech_10C4C929.wem"
     },
     {
      "Id": "432981530",
      "Language": "SFX",
      "Streaming": "false",
      "Location": "Memory",
      "ShortName": "AR_Aim.wav",
      "CachePath": "SFX/AR_Aim_10C4C929.wem"
     },
     {
      "Id": "470590754",
      "Language": "SFX",
      "Streaming": "false",
      "Location": "Memory",
      "ShortName": "AR_Shot_Tail_Spawn.wav",
      "CachePath": "SFX/AR_Shot_Tail_Spawn_10C4C929.wem"
     },
     {
      "Id": "548026506",
      "Language": "SFX",
      "Streaming": "false",
      "Location": "Memory",
      "ShortName": "AR_Empty_Rattle.wav",
      "CachePath": "SFX/AR_Empty_Rattle_10C4C929.wem"
     },
     {
      "Id": "624042849",
      "Language": "SFX",
      "Streaming": "false",
      "Location": "Memory",
      "ShortName": "GL_Reload.wav",
      "CachePath": "SFX/GL_Reload_10C4C929.wem"
     },
     {
      "Id": "635329318",
      "Language": "SFX",
      "Streaming": "false",
      "Location": "Memory",
      "ShortName": "AR_Shot_InitialTransient.wav",
      "CachePath": "SFX/AR_Shot_InitialTransient_10C4C929.wem"
     },
     {
      "Id": "669510815",
      "Language": "SFX",
      "Streaming": "false",
      "Location": "Memory",
      "ShortName": "GL_Equip.wav",
      "CachePath": "SFX/GL_Equip_10C4C929.wem"
     },
     {
      "Id": "687525484",
      "Language": "SFX",
      "Streaming": "false",
      "Location": "Memory",
      "ShortName": "GL_Aim.wav",
      "CachePath": "SFX/GL_Aim_10C4C929.wem"
     },
     {
      "Id": "781212311",
      "Language": "SFX",
      "Streaming": "false",
      "Location": "Memory",
      "ShortName": "AR_Reload.wav",
      "CachePath": "SFX/AR_Reload_10C4C929.wem"
     },
     {
      "Id": "811684578",
      "Language": "SFX",
      "Streaming": "false",
      "Location": "Memory",
      "ShortName": "GL_Dryfire.wav",
      "CachePath": "SFX/GL_Dryfire_10C4C929.wem"
     },
     {
      "Id": "869087166",
      "Language": "SFX",
      "Streaming": "false",
      "Location": "Memory",
      "ShortName": "AR_Equip.wav",
      "CachePath": "SFX/AR_Equip_10C4C929.wem"
     }
    ],
    "Plugins": {
     "ShareSets": [
      {
       "Id": "2080872166",
       "Name": "Brick_Wall_Minus_6dB_Peak_Fast_Release",
       "ObjectPath": "\\Effects\\Factory Effects\\Peak Limiter\\Brick_Wall_Minus_6dB_Peak_Fast_Release",
       "GUID": "{3FF9AD86-E377-40F8-970F-3D4EE73288B5}",
       "LibName": "Wwise Peak Limiter",
       "LibId": "7208963"
      }
     ]
    },
    "Events": [
     {
      "Id": "1694533419",
      "Name": "AR_Dryfire_OS",
      "ObjectPath": "\\Events\\Weapons\\Shooting\\Dryfire\\AR_Dryfire_OS",
      "GUID": "{1F162533-308D-4AB5-8A18-0D6E326EB1D8}",
      "DurationType": "OneShot",
      "DurationMin": "0.5",
      "DurationMax": "0.5",
      "MediaRefs": [
       {
        "Id": "304041726"
       }
      ],
      "AuxBusRefs": [
       {
        "Id": "3348775760",
        "Name": "Highrise_EarlyReflections",
        "ObjectPath": "\\Master-Mixer Hierarchy\\Default Work Unit\\Master Audio Bus\\Diegetic\\Auxiliaries\\Highrise\\Highrise_EarlyReflections",
        "GUID": "{EFDFADBC-CF4E-4A31-9DAB-28D0784E5E7D}"
       }
      ]
     },
     {
      "Id": "1260320770",
      "Name": "AR_Equip_OS",
      "ObjectPath": "\\Events\\Weapons\\Handling\\Equip\\AR_Equip_OS",
      "GUID": "{66D3D001-9957-4751-8B24-0C0AAD610ED4}",
      "DurationType": "OneShot",
      "DurationMin": "0.47193712",
      "DurationMax": "0.5297316",
      "MediaRefs": [
       {
        "Id": "869087166"
       }
      ],
      "AuxBusRefs": [
       {
        "Id": "3348775760",
        "Name": "Highrise_EarlyReflections",
        "ObjectPath": "\\Master-Mixer Hierarchy\\Default Work Unit\\Master Audio Bus\\Diegetic\\Auxiliaries\\Highrise\\Highrise_EarlyReflections",
        "GUID": "{EFDFADBC-CF4E-4A31-9DAB-28D0784E5E7D}"
       }
      ]
     },
     {
      "Id": "4263945094",
      "Name": "AR_Impact_OS",
      "ObjectPath": "\\Events\\Weapons\\Shooting\\Impact\\AR_Impact_OS",
      "GUID": "{873F24AE-5010-4080-8DFB-1C765AEC4801}",
      "MaxAttenuation": "0",
      "DurationType": "OneShot",
      "DurationMin": "0",
      "DurationMax": "0"
     },
     {
      "Id": "429698657",
      "Name": "AR_Reload_OS",
      "ObjectPath": "\\Events\\Weapons\\Reloading\\AR_Reload_OS",
      "GUID": "{6E436856-4CBE-4BA5-B184-21225058CE02}",
      "DurationType": "OneShot",
      "DurationMin": "1.6517799",
      "DurationMax": "1.8540605",
      "MediaRefs": [
       {
        "Id": "781212311"
       }
      ],
      "AuxBusRefs": [
       {
        "Id": "3348775760",
        "Name": "Highrise_EarlyReflections",
        "ObjectPath": "\\Master-Mixer Hierarchy\\Default Work Unit\\Master Audio Bus\\Diegetic\\Auxiliaries\\Highrise\\Highrise_EarlyReflections",
        "GUID": "{EFDFADBC-CF4E-4A31-9DAB-28D0784E5E7D}"
       }
      ]
     },
     {
      "Id": "3035132243",
      "Name": "AR_Shoot_LP",
      "ObjectPath": "\\Events\\Weapons\\Shooting\\Shoot\\AR_Shoot_LP",
      "GUID": "{027202E3-540C-4144-873B-7DCDD76899B6}",
      "DurationType": "Infinite",
      "MediaRefs": [
       {
        "Id": "635329318"
       }
      ],
      "AuxBusRefs": [
       {
        "Id": "3348775760",
        "Name": "Highrise_EarlyReflections",
        "ObjectPath": "\\Master-Mixer Hierarchy\\Default Work Unit\\Master Audio Bus\\Diegetic\\Auxiliaries\\Highrise\\Highrise_EarlyReflections",
        "GUID": "{EFDFADBC-CF4E-4A31-9DAB-28D0784E5E7D}"
       }
      ],
      "SwitchContainers": [
       {
        "SwitchValue": {
         "GroupType": "State",
         "GroupId": "747849153",
         "Id": "301467384",
         "GUID": "{2C1C780E-EFA5-4772-8620-E06CA40932F3}",
         "Default": "true"
        },
        "MediaRefs": [
         {
          "Id": "166846503"
         },
         {
          "Id": "228004887"
         },
         {
          "Id": "345176474"
         },
         {
          "Id": "373309000"
         },
         {
          "Id": "470590754"
         },
         {
          "Id": "548026506"
         }
        ],
        "PluginRefs": {
         "ShareSets": [
          {
           "Id": "2080872166"
          }
         ]
        }
       },
       {
        "SwitchValue": {
         "GroupType": "State",
         "GroupId": "747849153",
         "Id": "877225536",
         "GUID": "{E9597652-781B-4852-95B1-CADA7D874365}"
        },
        "MediaRefs": [
         {
          "Id": "166846503"
         },
         {
          "Id": "175929226"
         },
         {
          "Id": "228004887"
         },
         {
          "Id": "345176474"
         },
         {
          "Id": "373309000"
         },
         {
          "Id": "548026506"
         }
        ],
        "PluginRefs": {
         "ShareSets": [
          {
           "Id": "2080872166"
          }
         ]
        }
       },
       {
        "SwitchValue": {
         "GroupType": "State",
         "GroupId": "747849153",
         "Id": "748895195",
         "GUID": "{C7162D63-5030-4C71-878E-49C2A4492744}"
        },
        "MediaRefs": [
         {
          "Id": "166846503"
         },
         {
          "Id": "175929226"
         },
         {
          "Id": "228004887"
         },
         {
          "Id": "345176474"
         },
         {
          "Id": "373309000"
         },
         {
          "Id": "548026506"
         }
        ],
        "PluginRefs": {
         "ShareSets": [
          {
           "Id": "2080872166"
          }
         ]
        }
       },
       {
        "SwitchValue": {
         "GroupType": "State",
         "GroupId": "747849153",
         "Id": "1657765358",
         "GUID": "{8A683FAA-7476-4C8B-A437-13E5E8FE9888}"
        },
        "MediaRefs": [
         {
          "Id": "14501665"
         },
         {
          "Id": "166846503"
         },
         {
          "Id": "228004887"
         },
         {
          "Id": "345176474"
         },
         {
          "Id": "373309000"
         },
         {
          "Id": "548026506"
         }
        ],
        "PluginRefs": {
         "ShareSets": [
          {
           "Id": "2080872166"
          }
         ]
        }
       },
       {
        "SwitchValue": {
         "GroupType": "State",
         "GroupId": "747849153",
         "Id": "949156522",
         "GUID": "{72B927E3-2951-4E7F-B493-1DD0425F5518}"
        },
        "MediaRefs": [
         {
          "Id": "166846503"
         },
         {
          "Id": "175929226"
         },
         {
          "Id": "228004887"
         },
         {
          "Id": "345176474"
         },
         {
          "Id": "373309000"
         },
         {
          "Id": "548026506"
         }
        ],
        "PluginRefs": {
         "ShareSets": [
          {
           "Id": "2080872166"
          }
         ]
        }
       }
      ]
     },
     {
      "Id": "1883352941",
      "Name": "AR_WhizzBy_OS",
      "ObjectPath": "\\Events\\Weapons\\Shooting\\Travel\\AR_WhizzBy_OS",
      "GUID": "{DF281450-0700-404B-9DFD-8DBDC054CD38}",
      "MaxAttenuation": "0",
      "DurationType": "OneShot",
      "DurationMin": "0",
      "DurationMax": "0"
     },
     {
      "Id": "1764852559",
      "Name": "GL_Dryfire_OS",
      "ObjectPath": "\\Events\\Weapons\\Shooting\\Dryfire\\GL_Dryfire_OS",
      "GUID": "{EA2CD592-0394-4A84-919F-75A9F11F65BC}",
      "DurationType": "OneShot",
      "DurationMin": "0.5",
      "DurationMax": "0.5",
      "MediaRefs": [
       {
        "Id": "811684578"
       }
      ],
      "AuxBusRefs": [
       {
        "Id": "3348775760",
        "Name": "Highrise_EarlyReflections",
        "ObjectPath": "\\Master-Mixer Hierarchy\\Default Work Unit\\Master Audio Bus\\Diegetic\\Auxiliaries\\Highrise\\Highrise_EarlyReflections",
        "GUID": "{EFDFADBC-CF4E-4A31-9DAB-28D0784E5E7D}"
       }
      ]
     },
     {
      "Id": "3314806526",
      "Name": "GL_Equip_OS",
      "ObjectPath": "\\Events\\Weapons\\Handling\\Equip\\GL_Equip_OS",
      "GUID": "{15EF0405-429D-40BE-8769-103D030DBF08}",
      "DurationType": "OneShot",
      "DurationMin": "0.47193712",
      "DurationMax": "0.5297316",
      "MediaRefs": [
       {
        "Id": "669510815"
       }
      ],
      "AuxBusRefs": [
       {
        "Id": "3348775760",
        "Name": "Highrise_EarlyReflections",
        "ObjectPath": "\\Master-Mixer Hierarchy\\Default Work Unit\\Master Audio Bus\\Diegetic\\Auxiliaries\\Highrise\\Highrise_EarlyReflections",
        "GUID": "{EFDFADBC-CF4E-4A31-9DAB-28D0784E5E7D}"
       }
      ]
     },
     {
      "Id": "477299258",
      "Name": "GL_Impact_OS",
      "ObjectPath": "\\Events\\Weapons\\Shooting\\Impact\\GL_Impact_OS",
      "GUID": "{3FA3D47C-E701-4113-B86A-0EFBB1EE1241}",
      "MaxAttenuation": "0",
      "DurationType": "OneShot",
      "DurationMin": "0",
      "DurationMax": "0"
     },
     {
      "Id": "2238434314",
      "Name": "GL_PassBy_LP",
      "ObjectPath": "\\Events\\Weapons\\Shooting\\Travel\\GL_PassBy_LP",
      "GUID": "{566534D1-0C06-45CC-8878-334A29476347}",
      "MaxAttenuation": "0",
      "DurationType": "OneShot",
      "DurationMin": "0",
      "DurationMax": "0"
     },
     {
      "Id": "464045509",
      "Name": "GL_Reload_OS",
      "ObjectPath": "\\Events\\Weapons\\Reloading\\GL_Reload_OS",
      "GUID": "{778E484F-B81F-4DFB-8587-4CEA07B594B0}",
      "DurationType": "OneShot",
      "DurationMin": "2.7136385",
      "DurationMax": "3.0459566",
      "MediaRefs": [
       {
        "Id": "624042849"
       }
      ],
      "AuxBusRefs": [
       {
        "Id": "3348775760",
        "Name": "Highrise_EarlyReflections",
        "ObjectPath": "\\Master-Mixer Hierarchy\\Default Work Unit\\Master Audio Bus\\Diegetic\\Auxiliaries\\Highrise\\Highrise_EarlyReflections",
        "GUID": "{EFDFADBC-CF4E-4A31-9DAB-28D0784E5E7D}"
       }
      ]
     },
     {
      "Id": "1577363161",
      "Name": "GL_Shoot_OS",
      "ObjectPath": "\\Events\\Weapons\\Shooting\\Shoot\\GL_Shoot_OS",
      "GUID": "{314DB4B5-5CD0-4B6E-8803-898906F3175F}",
      "MaxAttenuation": "0",
      "DurationType": "OneShot",
      "DurationMin": "0",
      "DurationMax": "0"
     },
     {
      "Id": "3084237102",
      "Name": "WEP_Target_Engage_OS",
      "ObjectPath": "\\Events\\Weapons\\Targeting\\WEP_Target_Engage_OS",
      "GUID": "{59353546-680F-45BB-AFE9-59C7938042FE}",
      "DurationType": "OneShot",
      "DurationMin": "0.47193712",
      "DurationMax": "0.5297316",
      "AuxBusRefs": [
       {
        "Id": "3348775760",
        "Name": "Highrise_EarlyReflections",
        "ObjectPath": "\\Master-Mixer Hierarchy\\Default Work Unit\\Master Audio Bus\\Diegetic\\Auxiliaries\\Highrise\\Highrise_EarlyReflections",
        "GUID": "{EFDFADBC-CF4E-4A31-9DAB-28D0784E5E7D}"
       }
      ],
      "SwitchContainers": [
       {
        "SwitchValue": {
         "GroupType": "Switch",
         "GroupId": "2719266754",
         "Id": "1891117424",
         "GUID": "{6FE15811-998E-4E22-ACDE-9862762F2DA9}",
         "Default": "true"
        },
        "MediaRefs": [
         {
          "Id": "432981530"
         }
        ]
       },
       {
        "SwitchValue": {
         "GroupType": "Switch",
         "GroupId": "2719266754",
         "Id": "2886223932",
         "GUID": "{CC7198FF-EACB-450D-AAFA-A7B04554F707}"
        },
        "MediaRefs": [
         {
          "Id": "687525484"
         }
        ]
       }
      ]
     }
    ],
    "GameParameters": [
     {
      "Id": "2583655610",
      "Name": "PAR_AR_AmmoCount",
      "ObjectPath": "\\Game Parameters\\Weapons\\PAR_AR_AmmoCount",
      "GUID": "{14EB3BFB-E3DA-4C99-8306-D5E1B54679C6}"
     }
    ],
    "StateGroups": [
     {
      "Id": "747849153",
      "Name": "STA_LocationMix",
      "ObjectPath": "\\States\\Default Work Unit\\Highrise\\STA_LocationMix",
      "GUID": "{A0EBFE8C-DF3E-4501-9EA4-0DC220E20E4D}",
      "States": [
       {
        "Id": "301467384",
        "Name": "STA_Indoors_Spawn",
        "ObjectPath": "\\States\\Default Work Unit\\Highrise\\STA_LocationMix\\STA_Indoors_Spawn",
        "GUID": "{2C1C780E-EFA5-4772-8620-E06CA40932F3}"
       },
       {
        "Id": "748895195",
        "Name": "None",
        "ObjectPath": "\\States\\Default Work Unit\\Highrise\\STA_LocationMix\\None",
        "GUID": "{C7162D63-5030-4C71-878E-49C2A4492744}"
       },
       {
        "Id": "877225536",
        "Name": "STA_Outdoors_Atrium",
        "ObjectPath": "\\States\\Default Work Unit\\Highrise\\STA_LocationMix\\STA_Outdoors_Atrium",
        "GUID": "{E9597652-781B-4852-95B1-CADA7D874365}"
       },
       {
        "Id": "949156522",
        "Name": "STA_Outdoors_Balcony_Center",
        "ObjectPath": "\\States\\Default Work Unit\\Highrise\\STA_LocationMix\\STA_Outdoors_Balcony_Center",
        "GUID": "{72B927E3-2951-4E7F-B493-1DD0425F5518}"
       },
       {
        "Id": "1657765358",
        "Name": "STA_Indoors_Room",
        "ObjectPath": "\\States\\Default Work Unit\\Highrise\\STA_LocationMix\\STA_Indoors_Room",
        "GUID": "{8A683FAA-7476-4C8B-A437-13E5E8FE9888}"
       }
      ]
     }
    ],
    "SwitchGroups": [
     {
      "Id": "2719266754",
      "Name": "SWT_Weapon_Types",
      "ObjectPath": "\\Switches\\Default Work Unit\\SWT_Weapon_Types",
      "GUID": "{ECBD5BFD-ACAD-4CAA-BBDC-95A58B4A93D2}",
      "Switches": [
       {
        "Id": "1891117424",
        "Name": "AR_Equipped",
        "ObjectPath": "\\Switches\\Default Work Unit\\SWT_Weapon_Types\\AR_Equipped",
        "GUID": "{6FE15811-998E-4E22-ACDE-9862762F2DA9}"
       },
       {
        "Id": "2886223932",
        "Name": "GL_Equipped",
        "ObjectPath": "\\Switches\\Default Work Unit\\SWT_Weapon_Types\\GL_Equipped",
        "GUID": "{CC7198FF-EACB-450D-AAFA-A7B04554F707}"
       }
      ]
     }
    ]
   }
  ],
  "FileHash": "{856ED698-C9DB-7CE0-871F-9AF5E3C6D943}"
 }
}