<?xml version="1.0" encoding="utf-8"?>
<SoundBanksInfo Platform="Windows" BasePlatform="Windows" SchemaVersion="16" SoundBankVersion="145">
	<SoundBanks>
		<SoundBank Id="3466276443" Type="Bus" GUID="{452ECF50-CE27-4E43-BF81-B393DD3BEE9B}" Language="SFX" Hash="{D423A80F-B5A0-FDB9-91D5-3890BB507956}">
			<ObjectPath>Highrise_Atrium</ObjectPath>
			<ShortName>Highrise_Atrium</ShortName>
			<Path>Bus/Highrise_Atrium.bnk</Path>
			<Plugins>
				<ShareSets>
					<Plugin Id="602546716" Name="Room_Large" ObjectPath="\Effects\Factory Effects\RoomVerb\Rooms\Room_Large" GUID="{AD8EFAFC-7121-4D5F-BE4D-B13FBD6CEBAE}" LibName="Wwise RoomVerb" LibId="7733251"/>
				</ShareSets>
			</Plugins>
			<AuxBusses>
				<AuxBus Id="3466276443" Name="Highrise_Atrium" ObjectPath="\Master-Mixer Hierarchy\Default Work Unit\Master Audio Bus\Diegetic\Auxiliaries\Highrise\Highrise_Atrium" GUID="{452ECF50-CE27-4E43-BF81-B393DD3BEE9B}">
					<PluginRefs>
						<ShareSets>
							<PluginRef Id="602546716"/>
						</ShareSets>
					</PluginRefs>
				</AuxBus>
			</AuxBusses>
		</SoundBank>
	</SoundBanks>
	<FileHash>{DADF6C63-DB5C-4E88-7427-117D80B4B39B}</FileHash>
</SoundBanksInfo>
